opensesame/__init__.py
opensesame/opensesame.py
opensesame/test.py
opensesame_sdk-0.2.7.dist-info/LICENSE
opensesame_sdk-0.2.7.dist-info/METADATA
opensesame_sdk-0.2.7.dist-info/WHEEL
opensesame_sdk-0.2.7.dist-info/top_level.txt
opensesame_sdk-0.2.7.dist-info/RECORD
