Metadata-Version: 2.1
Name: opensesame-sdk
Version: 0.2.7
Summary: A custom OpenAI client with OpenSesame integration
Author: Anthony Azrak
Author-email: anthony@opensesame.dev
Classifier: Development Status :: 3 - Alpha
Classifier: Intended Audience :: Developers
Classifier: License :: OSI Approved :: MIT License
Classifier: Operating System :: OS Independent
Classifier: Programming Language :: Python :: 3
Classifier: Programming Language :: Python :: 3.7
Classifier: Programming Language :: Python :: 3.8
Classifier: Programming Language :: Python :: 3.9
Requires-Python: >=3.7
License-File: LICENSE
Requires-Dist: openai
Requires-Dist: requests
Requires-Dist: google-generativeai
Requires-Dist: anthropic
Requires-Dist: groq
Requires-Dist: cohere
Requires-Dist: langchain-openai
Requires-Dist: langchain
